MANIFEST.in
README.rst
distribute_setup.py
setup.py
wpmd.py
wp_md.egg-info/PKG-INFO
wp_md.egg-info/SOURCES.txt
wp_md.egg-info/dependency_links.txt
wp_md.egg-info/entry_points.txt
wp_md.egg-info/top_level.txt